casper7_plugin_wordle_reactions/__init__.py
casper7_plugin_wordle_reactions/run.py
casper7_plugin_wordle_reactions/settings.py
casper7_plugin_wordle_reactions-0.8.0.dist-info/entry_points.txt
casper7_plugin_wordle_reactions-0.8.0.dist-info/WHEEL
casper7_plugin_wordle_reactions-0.8.0.dist-info/METADATA
casper7_plugin_wordle_reactions-0.8.0.dist-info/RECORD
