Metadata-Version: 2.1
Name: casper7-plugin-wordle-reactions
Version: 0.8.0
Summary: a casper7 plugin that reacts to wordle results
Home-page: https://github.com/backwardspy/casper7-plugin-wordle-reactions
License: MIT
Author: backwardspy
Author-email: backwardspy@gmail.com
Requires-Python: >=3.10,<4.0
Classifier: License :: OSI Approved :: MIT License
Classifier: Programming Language :: Python :: 3
Classifier: Programming Language :: Python :: 3.10
Classifier: Programming Language :: Python :: 3.11
Requires-Dist: docopt-ng (>=0.8.1,<0.9.0)
Requires-Dist: pydantic (>=1.10.2,<2.0.0)
Project-URL: Repository, https://github.com/backwardspy/casper7-plugin-wordle-reactions
